{"cameraMode":{"drawMode":0,"name":"Shaded","section":"Shading Mode"},"sceneLighting":false,"audioPlay":false,"sceneViewState":{"m_AlwaysRefresh":false,"showFog":true,"showSkybox":false,"showFlares":true,"showImageEffects":true,"showParticleSystems":true,"showVisualEffectGraphs":true,"m_FxEnabled":true},"in2DMode":false,"pivot":{"x":17.5,"y":2.4600000381469728,"z":6.75},"rotation":{"x":0.15315982699394227,"y":-0.7033607363700867,"z":0.15940867364406587,"w":0.6756269335746765},"size":2.9373531341552736,"orthographic":false}